nba/__init__.py
nba/__main__.py
nba/cli.py
nba/fetch_data.py
nba/scores.py
nba/standings.py
nba_scores-0.1.7.dist-info/licenses/LICENSE
nba_scores-0.1.7.dist-info/METADATA
nba_scores-0.1.7.dist-info/WHEEL
nba_scores-0.1.7.dist-info/entry_points.txt
nba_scores-0.1.7.dist-info/top_level.txt
nba_scores-0.1.7.dist-info/RECORD
