Metadata-Version: 2.4
Name: nba-scores
Version: 0.1.7
Summary: A CLI interface to get current NBA scores and standings.
Author-email: Christian Cleberg <hello@cmc.pub>
License-Expression: GPL-3.0-or-later
Project-URL: Homepage, https://github.com/ccleberg/nba-scores
Project-URL: Issues, https://github.com/ccleberg/nba-scores/issues
Classifier: Programming Language :: Python :: 3
Classifier: Operating System :: OS Independent
Requires-Python: >=3.8
License-File: LICENSE
Requires-Dist: nba_api
Requires-Dist: tabulate
Requires-Dist: argparse
Dynamic: license-file
